cli/__init__.py
cli/config.py
cli/main.py
cli/__tests__/__init__.py
cli/__tests__/conftest.py
cli/__tests__/test_summary_writer.py
cli/summarizer/__init__.py
cli/summarizer/base.py
cli/summarizer/exceptions.py
cli/summarizer/models.py
cli/summarizer/ollama.py
cli/summarizer/prompt.py
cli/summarizer/utils/__init__.py
cli/summarizer/utils/logging.py
cli/summarizer/utils/preprocessors.py
cli/summarizer/utils/retry.py
cli/summarizer/utils/simple_tokenizer.py
cli/summarizer/utils/token_budget_segmenter.py
nitrodigest_cli-0.3.0.dist-info/licenses/LICENSE
nitrodigest_cli-0.3.0.dist-info/METADATA
nitrodigest_cli-0.3.0.dist-info/WHEEL
nitrodigest_cli-0.3.0.dist-info/entry_points.txt
nitrodigest_cli-0.3.0.dist-info/top_level.txt
nitrodigest_cli-0.3.0.dist-info/RECORD
