Metadata-Version: 2.4
Name: nitrodigest-cli
Version: 0.3.0
Summary: The privacy‑first, local‑LLM text‑summariser for developers.
Home-page: https://github.com/Frodigo/garage/tree/main/Projects/Nitrodigest/Cli
Author: Marcin Kwiatkowski
Author-email: marcin@frodigo.com
Classifier: Programming Language :: Python :: 3
Classifier: Operating System :: OS Independent
Requires-Python: >=3.6
License-File: LICENSE
Requires-Dist: requests>=2.28.0
Requires-Dist: pyyaml>=6.0
Requires-Dist: nltk>=3.9.1
Requires-Dist: emoji>=2.14.1
Requires-Dist: tqdm>=4.67.1
Dynamic: license-file
